[
  {"native_text":"おはようございます","target_text":"อรุณสวัสดิ์","pronunciation":"ʔà-run sa-wàt","genre":"基礎共通","memo":"朝の丁寧な挨拶。ニュース等で使われますが、日常はサワッディーでも十分です。","favorite":false,"wrongCount":0,"id":"gre-7a2b-41c9-bcde-000000000001"},
  {"native_text":"こんにちは","target_text":"สวัสดี","pronunciation":"sa-wàt-diī","genre":"基礎共通","memo":"万能な挨拶。男性は khráp、女性は khâ を語尾に付けるのがマナーです。","favorite":false,"wrongCount":0,"id":"gre-8b3c-52d0-cdba-000000000002"},
  {"native_text":"こんばんは","target_text":"สวัสดี","pronunciation":"sa-wàt-diī","genre":"基礎共通","memo":"夜も「サワッディー」で問題ありません。時間帯を問わず使えます。","favorite":false,"wrongCount":0,"id":"gre-9c4d-63e1-deab-000000000003"},
  {"native_text":"さようなら","target_text":"ลาก่อน","pronunciation":"laā-kòn","genre":"基礎共通","memo":"しばらく会わない時の別れ。普段は「サワッディー」で別れるのが一般的です。","favorite":false,"wrongCount":0,"id":"gre-0d5e-74f2-effc-000000000004"},
  {"native_text":"またね","target_text":"เจอกันนะ","pronunciation":"tɕə̄ː-kan-náʔ","genre":"基礎共通","memo":"「また会おうね」という親しい間柄でのカジュアルな表現。","favorite":false,"wrongCount":0,"id":"gre-1e6f-8503-faae-000000000005"},
  {"native_text":"おやすみなさい","target_text":"ฝันดี","pronunciation":"fǎn-diī","genre":"基礎共通","memo":"直訳は「良い夢を」。寝る前の定番フレーズです。","favorite":false,"wrongCount":0,"id":"gre-2f7a-9614-abdf-000000000006"},
  {"native_text":"お元気ですか？","target_text":"สบายดีไหม","pronunciation":"sa-baāy-diī-mǎy","genre":"基礎共通","memo":"サバイ（心地よい）ディー（良い）マイ（？）。最も一般的な健康伺いです。","favorite":false,"wrongCount":0,"id":"int-3a8b-0725-bced-000000000007"},
  {"native_text":"元気です、ありがとう","target_text":"สบายดี ขอบคุณ","pronunciation":"sa-baāy-diī khòːp-khun","genre":"基礎共通","memo":"返事の定番。khòːp-khun（ありがとう）を添えると丁寧です。","favorite":false,"wrongCount":0,"id":"int-4b9c-1836-cdef-000000000008"},
  {"native_text":"まあまあです","target_text":"ก็ดี","pronunciation":"kɔ̂ː-diī","genre":"基礎共通","memo":"「まずまずです、悪くないです」といったニュアンスです。","favorite":false,"wrongCount":0,"id":"int-5c0d-2947-defa-000000000009"},
  {"native_text":"疲れています","target_text":"เหนื่อย","pronunciation":"nɯ̀ay","genre":"基礎共通","memo":"疲労を伝える言葉。低く抑えるように発音します。","favorite":false,"wrongCount":0,"id":"int-6d1e-3058-efab-000000000010"},
  {"native_text":"ありがとうございます","target_text":"ขอบคุณ","pronunciation":"khòːp-khun","genre":"基礎共通","memo":"感謝の基本。手を胸の前で合わせる（ワイ）動作を伴うと非常に丁寧です。","favorite":false,"wrongCount":0,"id":"bas-7e2f-4169-facb-000000000011"},
  {"native_text":"どういたしまして","target_text":"ยินดี","pronunciation":"jin-diī","genre":"基礎共通","memo":"直訳は「喜んで」。お礼への返答として広く使われます。","favorite":false,"wrongCount":0,"id":"bas-8f3a-5270-abcd-000000000012"},
  {"native_text":"こちらこそ","target_text":"เช่นกัน","pronunciation":"tɕʰêːn-kan","genre":"基礎共通","memo":"「同じく、こちらこそ」という意味。相手が良い言葉をくれた時に。","favorite":false,"wrongCount":0,"id":"bas-9a4b-6381-bcde-000000000013"},
  {"native_text":"すみません","target_text":"ขอโทษ","pronunciation":"khɔ̌ː-thôːt","genre":"基礎共通","memo":"謝罪、呼びかけの両方に使えます。非常に多用するフレーズです。","favorite":false,"wrongCount":0,"id":"bas-0b5c-7492-cdef-000000000014"},
  {"native_text":"ごめんなさい","target_text":"ขอโทษ","pronunciation":"khɔ̌ː-thôːt","genre":"基礎共通","memo":"謝る時も同じフレーズです。深刻な時は動作も丁寧に行います。","favorite":false,"wrongCount":0,"id":"bas-1c6d-8503-defa-000000000015"},
  {"native_text":"大丈夫ですよ","target_text":"ไม่เป็นไร","pronunciation":"mây-pen-rāy","genre":"基礎共通","memo":"タイ人の国民性を象徴する「気にしないで」「どういたしまして」の意。","favorite":false,"wrongCount":0,"id":"bas-2d7e-9614-efab-000000000016"},
  {"native_text":"気にしないで","target_text":"ไม่เป็นไร","pronunciation":"mây-pen-rāy","genre":"基礎共通","memo":"「マイペンライ」はミスを許す魔法の言葉です。","favorite":false,"wrongCount":0,"id":"bas-3e8f-0725-fabc-000000000017"},
  {"native_text":"はい","target_text":"ใช่ / ครับ / ค่ะ","pronunciation":"tɕʰây / kʰráp / kʰâʔ","genre":"基礎共通","memo":"「その通り」はチャイ、返事としての「はい」はクラップ/カを使います。","favorite":false,"wrongCount":0,"id":"bas-4f9a-1836-abcd-000000000018"},
  {"native_text":"いいえ","target_text":"ไม่ / ไม่ใช่","pronunciation":"mây / mây-tɕʰây","genre":"基礎共通","memo":"否定語のマイを前に。違います、という時はマイチャイ。","favorite":false,"wrongCount":0,"id":"bas-5a0b-2947-bcde-000000000019"},
  {"native_text":"理解できましたか？","target_text":"เข้าใจไหม","pronunciation":"khâw-tɕāy-mǎy","genre":"基礎共通","memo":"カオ・ヂャイ（理解する）＋マイ（？）。心に入りましたか、が語源。","favorite":false,"wrongCount":0,"id":"lea-6b1c-3058-cdef-000000000020"},
  {"native_text":"はい、わかりました","target_text":"เข้าใจแล้ว","pronunciation":"khâw-tɕāy-lɛ́ːw","genre":"基礎共通","memo":"レオ（～した、もう）を付けて、完了を伝えます。","favorite":false,"wrongCount":0,"id":"lea-7c2d-4169-defa-000000000021"},
  {"native_text":"いいえ、わかりません","target_text":"ไม่เข้าใจ","pronunciation":"mây-khâw-tɕāy","genre":"基礎共通","memo":"正直に伝えることで、相手が言い方を変えてくれるきっかけになります。","favorite":false,"wrongCount":0,"id":"lea-8d3e-5270-efab-000000000022"},
  {"native_text":"もう一度言っていただけますか？","target_text":"พูดอีกทีได้ไหม","pronunciation":"pʰûːt-ìːk-tʰiī-dâay-mǎy","genre":"基礎共通","memo":"プート（話す）イークティー（もう一度）ダイマイ（できる？）。","favorite":false,"wrongCount":0,"id":"lea-9e4f-6381-fabc-000000000023"},
  {"native_text":"ゆっくり話してください","target_text":"พูดช้าๆ หน่อย","pronunciation":"pʰûːt-tɕʰâː-tɕʰâː-nɔ̀y","genre":"基礎共通","memo":"チャー（遅い）を2回繰り返します。ノイは「少し/～してください」の響き。","favorite":false,"wrongCount":0,"id":"lea-0f5a-7492-abcd-000000000024"},
  {"native_text":"「〇〇」はどういう意味ですか？","target_text":"〇〇 แปลว่าอะไร","pronunciation":"〇〇 plɛ̄ː-wâː-ʔà-rāy","genre":"基礎共通","memo":"単語や概念の意味を尋ねる時に必須です。","favorite":false,"wrongCount":0,"id":"lea-1a6b-8503-bcde-000000000025"},
  {"native_text":"これはタイ語で何と言いますか？","target_text":"อันนี้ภาษาไทยเรียกว่าอะไร","pronunciation":"ʔan-nií-pʰaā-sǎː-tʰāy-rîak-wâː-ʔà-rāy","genre":"基礎共通","memo":"アンニー（これ）パーサータイ（タイ語）リーヤックワー（～と呼ぶ）。","favorite":false,"wrongCount":0,"id":"lea-2b7c-9614-cdef-000000000026"},
  {"native_text":"書いていただけますか？","target_text":"เขียนให้หน่อยได้ไหม","pronunciation":"khǐan-hây-nɔ̀y-dâay-mǎy","genre":"基礎共通","memo":"発音が難しくて聞き取れない時に有効な手段です。","favorite":false,"wrongCount":0,"id":"lea-3c8d-0725-defa-000000000027"},
  {"native_text":"ちょっと待ってください","target_text":"รอก่อนนะ","pronunciation":"rɔ̄ː-kòn-náʔ","genre":"基礎共通","memo":"ロー（待つ）コン（先に/とりあえず）。ナは語調を整える終助詞。","favorite":false,"wrongCount":0,"id":"bas-4d9e-1836-efab-000000000028"},
  {"native_text":"助けていただけますか？","target_text":"ช่วยหน่อยได้ไหม","pronunciation":"tɕʰûay-nɔ̀y-dâay-mǎy","genre":"基礎共通","memo":"チュアイ（助ける）。日常の手伝いから緊急事態まで使えます。","favorite":false,"wrongCount":0,"id":"bas-5e0f-2947-fabc-000000000029"},
  {"native_text":"もちろんです","target_text":"แน่นอน","pronunciation":"nɛ̂ː-nɔ̄ːn","genre":"基礎共通","memo":"強い肯定や、快く引き受ける時の表現。","favorite":false,"wrongCount":0,"id":"bas-6f1a-3058-abcd-000000000030"},
  {"native_text":"すみません、今はできません","target_text":"ขอโทษ ตอนนี้ทำไม่ได้","pronunciation":"khɔ̌ː-thôːt tɔ̄ːn-nií-tʰam-mây-dâay","genre":"基礎共通","memo":"丁寧に断る時。タム・マイ・ダイ（できない）。","favorite":false,"wrongCount":0,"id":"bas-7a2b-4169-bcde-000000000031"},
  {"native_text":"お名前は何ですか？","target_text":"คุณชื่ออะไร","pronunciation":"khun-tɕʰɯ̂ː-ʔà-rāy","genre":"基礎共通","memo":"クン（あなた）チュー（名前）アライ（何）。基本中の基本。","favorite":false,"wrongCount":0,"id":"sel-8b3c-5270-cdef-000000000032"},
  {"native_text":"私の名前は〇〇です","target_text":"ผม/ฉันชื่อ 〇〇","pronunciation":"pʰǒm/tɕʰǎn-tɕʰɯ̂ː 〇〇","genre":"基礎共通","memo":"男性はポム、女性はチャンを使い分けます。","favorite":false,"wrongCount":0,"id":"sel-9c4d-6381-defa-000000000033"},
  {"native_text":"お会いできて嬉しいです","target_text":"ยินดีที่ได้รู้จัก","pronunciation":"jin-diī-tʰîː-dâay-rúː-tɕàk","genre":"基礎共通","memo":"初対面の会話を和やかに終わらせるフレーズ。","favorite":false,"wrongCount":0,"id":"sel-0d5e-7492-efab-000000000034"},
  {"native_text":"どちらから来ましたか？","target_text":"มาจากไหน","pronunciation":"maā-tɕàːk-nǎy","genre":"基礎共通","memo":"出身を聞く時に使います。ナイ（どこ）。","favorite":false,"wrongCount":0,"id":"sel-1e6f-8503-fabc-000000000035"},
  {"native_text":"日本から来ました","target_text":"มาจากญี่ปุ่น","pronunciation":"maā-tɕàːk-jiî-pùn","genre":"基礎共通","memo":"イープン（日本）。タイ人は日本にとても好意的です。","favorite":false,"wrongCount":0,"id":"sel-2f7a-9614-abcd-000000000036"},
  {"native_text":"東京に住んでいます","target_text":"อยู่ที่โตเกียว","pronunciation":"jùː-tʰîː-toō-kīaw","genre":"基礎共通","memo":"ユーティー（～にいる）＋地名。","favorite":false,"wrongCount":0,"id":"sel-3a8b-0725-bcde-000000000037"},
  {"native_text":"お仕事は何をされていますか？","target_text":"ทำงานอะไร","pronunciation":"tʰam-ŋaān-ʔà-rāy","genre":"基礎共通","memo":"タムガーン（働く）。タイでは職業をよく尋ね合います。","favorite":false,"wrongCount":0,"id":"sel-4b9c-1836-cdef-000000000038"},
  {"native_text":"会社員です","target_text":"พนักงานบริษัท","pronunciation":"pʰa-nák-ŋaān-bɔ̄ː-ri-sàt","genre":"基礎共通","memo":"パナックガーン（職員）ボリサット（会社）。","favorite":false,"wrongCount":0,"id":"sel-5c0d-2947-defa-000000000039"},
  {"native_text":"学生です","target_text":"นักเรียน","pronunciation":"nák-riian","genre":"基礎共通","memo":"リアン（学ぶ）。大学生ならナックスクサーと言います。","favorite":false,"wrongCount":0,"id":"sel-6d1e-3058-efab-000000000040"},
  {"native_text":"主婦（主夫）です","target_text":"แม่บ้าน","pronunciation":"mɛ̂ː-bâːn","genre":"基礎共通","memo":"直訳は「家の母」。お手伝いさんを呼ぶ時もメーバーンと言います。","favorite":false,"wrongCount":0,"id":"sel-7e2f-4169-fabc-000000000041"},
  {"native_text":"私はマーケティングの仕事をしています","target_text":"ทำงานด้านการตลาด","pronunciation":"tʰam-ŋaān-dâːn-kaān-tà-làːt","genre":"基礎共通","memo":"ガーン・タラート（市場/マーケティング）。","favorite":false,"wrongCount":0,"id":"sel-8f3a-5270-abcd-000000000042"},
  {"native_text":"タイ語が話せますか？","target_text":"พูดภาษาไทยได้ไหม","pronunciation":"pʰûːt-pʰaā-sǎː-tʰāy-dâay-mǎy","genre":"基礎共通","memo":"パーサータイ（タイ語）。ダイマイ（できますか？）。","favorite":false,"wrongCount":0,"id":"sel-9a4b-6381-bcde-000000000043"},
  {"native_text":"少し話せます","target_text":"พูดได้นิดหน่อย","pronunciation":"pʰûːt-dâay-nít-nɔ̀y","genre":"基礎共通","memo":"ニッノイ（少し）。学習者が多用するフレーズ。","favorite":false,"wrongCount":0,"id":"sel-0b5c-7492-cdef-000000000044"},
  {"native_text":"まだ勉強中です","target_text":"กำลังเรียนอยู่","pronunciation":"kam-laŋ-riian-jùː","genre":"基礎共通","memo":"ガムラン～ユーで現在進行形を表します。","favorite":false,"wrongCount":0,"id":"sel-1c6d-8503-defa-000000000045"},
  {"native_text":"何歳ですか？","target_text":"อายุเท่าไหร่","pronunciation":"ʔaā-júʔ-tʰâw-rày","genre":"基礎共通","memo":"アーユ（年齢）タオライ（いくら）。タイでは年齢をよく聞きます。","favorite":false,"wrongCount":0,"id":"sel-2d7e-9614-efab-000000000046"},
  {"native_text":"〇〇歳です","target_text":"อายุ 〇〇 ปี","pronunciation":"ʔaā-júʔ 〇〇 piī","genre":"基礎共通","memo":"ピー（年）。数字の読み方を覚えるチャンスです。","favorite":false,"wrongCount":0,"id":"sel-3e8f-0725-fabc-000000000047"},
  {"native_text":"兄弟はいますか？","target_text":"มีพี่น้องไหม","pronunciation":"miī-pʰîː-nɔ́ːŋ-mǎy","genre":"基礎共通","memo":"ピー（兄姉）ノーン（弟妹）。家族を大切にする文化です。","favorite":false,"wrongCount":0,"id":"sel-4f9a-1836-abcd-000000000048"},
  {"native_text":"姉が一人います","target_text":"มีพี่สาวหนึ่งคน","pronunciation":"miī-pʰîː-sǎːw-nɯ̀ŋ-khōn","genre":"基礎共通","memo":"ピーサーオ（姉）。コンは人を数える助数詞。","favorite":false,"wrongCount":0,"id":"sel-5a0b-2947-bcde-000000000049"},
  {"native_text":"一人っ子です","target_text":"เป็นลูกคนเดียว","pronunciation":"pēn-lûːk-khōn-diiaw","genre":"基礎共通","memo":"ルーク（子供）コンディヤオ（唯一の人）。","favorite":false,"wrongCount":0,"id":"sel-6b1c-3058-cdef-000000000050"},
  {"native_text":"趣味は何ですか？","target_text":"งานอดิเรกคืออะไร","pronunciation":"ŋaān-ʔà-di-rèːk-khɯ̄ː-ʔà-rāy","genre":"基礎共通","memo":"ガーン・アディレーク（趣味）。少し格式高い言葉。","favorite":false,"wrongCount":0,"id":"sel-7c2d-4169-defa-000000000051"},
  {"native_text":"映画を見ることです","target_text":"ชอบดูหนัง","pronunciation":"tɕʰɔ̂ːp-duū-nǎŋ","genre":"基礎共通","memo":"チョープ（好き）ドゥー（見る）ナン（映画）。","favorite":false,"wrongCount":0,"id":"sel-8d3e-5270-efab-000000000052"},
  {"native_text":"旅行が好きです","target_text":"ชอบเที่ยว","pronunciation":"tɕʰɔ̂ːp-tʰîaw","genre":"基礎共通","memo":"ティアオは遊びや観光、ぶらぶらすること全般を指します。","favorite":false,"wrongCount":0,"id":"sel-9e4f-6381-fabc-000000000053"},
  {"native_text":"好きな食べ物は何ですか？","target_text":"ชอบกินอะไร","pronunciation":"tɕʰɔ̂ːp-kin-ʔà-rāy","genre":"基礎共通","memo":"キン（食べる）。食事の話はタイ人と仲良くなる近道。","favorite":false,"wrongCount":0,"id":"sel-0f5a-7492-abcd-000000000054"},
  {"native_text":"寿司が好きです","target_text":"ชอบกินซูชิ","pronunciation":"tɕʰɔ̂ːp-kin-suū-tɕʰíʔ","genre":"基礎共通","memo":"日本料理はタイで大人気です。","favorite":false,"wrongCount":0,"id":"sel-1a6b-8503-bcde-000000000055"},
  {"native_text":"甘いものは苦手です","target_text":"ไม่ชอบของหวาน","pronunciation":"mây-tɕʰɔ̂ːp-khɔ̌ːŋ-wǎːn","genre":"基礎共通","memo":"コーン・ワーン（甘いもの）。タイの飲み物は基本甘いので便利。","favorite":false,"wrongCount":0,"id":"sel-2b7c-9614-cdef-000000000056"},
  {"native_text":"連絡先を交換しませんか？","target_text":"ขอไลน์หน่อยได้ไหม","pronunciation":"khɔ̌ː-laāy-nɔ̀y-dâay-mǎy","genre":"基礎共通","memo":"タイでは主要な連絡手段がLINEなのでこう言います。","favorite":false,"wrongCount":0,"id":"sel-3c8d-0725-defa-000000000057"},
  {"native_text":"いいですよ","target_text":"ได้","pronunciation":"dâay","genre":"基礎共通","memo":"「可能、OK」を表す非常に汎用性の高い一言。","favorite":false,"wrongCount":0,"id":"sel-4d9e-1836-efab-000000000058"},
  {"native_text":"SNSをやっていますか？","target_text":"เล่นโซเชียลไหม","pronunciation":"lên-soō-tɕʰîal-mǎy","genre":"基礎共通","memo":"レン（遊ぶ/操作する）。FacebookやIGを指します。","favorite":false,"wrongCount":0,"id":"sel-5e0f-2947-fabc-000000000059"},
  {"native_text":"トイレはどこですか？","target_text":"ห้องน้ำอยู่ที่ไหน","pronunciation":"hɔ̂ŋ-náːm-jùː-tʰîː-nǎy","genre":"基礎共通","memo":"ホーン・ナーム（トイレ）。生存に必須の言葉。","favorite":false,"wrongCount":0,"id":"tra-6f1a-3058-abcd-000000000060"},
  {"native_text":"あちらです","target_text":"อยู่ตรงนั้น","pronunciation":"jùː-trōŋ-nán","genre":"基礎共通","memo":"トロン・ナン（あそこ）。指を差して教えてくれます。","favorite":false,"wrongCount":0,"id":"tra-7a2b-4169-bcde-000000000061"},
  {"native_text":"角を曲がったところにあります","target_text":"อยู่ตรงหัวมุม","pronunciation":"jùː-trōŋ-hǔa-mūm","genre":"基礎共通","memo":"フアムム（角）。場所の説明によく使われます。","favorite":false,"wrongCount":0,"id":"tra-8b3c-5270-cdef-000000000062"},
  {"native_text":"駅はどこですか？","target_text":"สถานีอยู่ที่ไหน","pronunciation":"sa-tʰǎː-niī-jùː-tʰîː-nǎy","genre":"基礎共通","memo":"サターニー（駅）。","favorite":false,"wrongCount":0,"id":"tra-9c4d-6381-defa-000000000063"},
  {"native_text":"ホテルはどこですか？","target_text":"โรงแรมอยู่ที่ไหน","pronunciation":"rōːŋ-rɛ̄ːm-jùː-tʰîː-nǎy","genre":"基礎共通","memo":"ローンレーム（ホテル）。","favorite":false,"wrongCount":0,"id":"tra-0d5e-7492-efab-000000000064"},
  {"native_text":"地図で教えてくれますか？","target_text":"ช่วยดูในแผนที่หน่อย","pronunciation":"tɕʰûay-duū-nāy-pʰɛ̌ːn-tʰîː-nɔ̀y","genre":"基礎共通","memo":"ペーンティー（地図）。スマホを見せる時に有効。","favorite":false,"wrongCount":0,"id":"tra-1e6f-8503-fabc-000000000065"},
  {"native_text":"ここから遠いですか？","target_text":"ไกลจากที่นี่ไหม","pronunciation":"klāy-tɕàːk-tʰîː-niī-mǎy","genre":"基礎共通","memo":"クライ（遠い）。暑いタイでは距離確認が大事。","favorite":false,"wrongCount":0,"id":"tra-2f7a-9614-abcd-000000000066"},
  {"native_text":"歩いて5分です","target_text":"เดินห้านาที","pronunciation":"də̄ːn-hâː-naā-tʰiī","genre":"基礎共通","memo":"ドゥーン（歩く）ハー（5）ナーティー（分）。","favorite":false,"wrongCount":0,"id":"tra-3a8b-0725-bcde-000000000067"},
  {"native_text":"タクシーが必要です","target_text":"ต้องไปแท็กซี่","pronunciation":"tɔ̂ŋ-pāy-tʰɛ́k-siî","genre":"基礎共通","memo":"トーン（必要）パイ（行く）。テクシーはそのまま通じます。","favorite":false,"wrongCount":0,"id":"tra-4b9c-1836-cdef-000000000068"},
  {"native_text":"チケットを1枚ください","target_text":"ขอตั๋วหนึ่งใบ","pronunciation":"khɔ̌ː-tǔa-nɯ̀ŋ-bāy","genre":"基礎共通","memo":"トア（切符）。バイは紙類を数える助数詞。","favorite":false,"wrongCount":0,"id":"tra-5c0d-2947-defa-000000000069"},
  {"native_text":"〇〇へはどう行けばいいですか？","target_text":"ไป 〇〇 ยังไง","pronunciation":"pāy 〇〇 jaŋ-ŋāy","genre":"基礎共通","memo":"ヤンガイ（どのように）。移動の相談に便利。","favorite":false,"wrongCount":0,"id":"tra-6d1e-3058-efab-000000000070"},
  {"native_text":"次の電車は何時ですか？","target_text":"รถไฟเที่ยวต่อไปกี่โมง","pronunciation":"rót-fāy-tʰîaw-tɔ̀ː-pāy-kìː-moōŋ","genre":"基礎共通","memo":"ロットファイ（電車）キーモーン（何時）。","favorite":false,"wrongCount":0,"id":"tra-7e2f-4169-fabc-000000000071"},
  {"native_text":"ここに座ってもいいですか？","target_text":"ขอนั่งตรงนี้ได้ไหม","pronunciation":"khɔ̌ː-nâŋ-trōŋ-nií-dâay-mǎy","genre":"基礎共通","memo":"ナン（座る）。混雑した店などで許可を求める時。","favorite":false,"wrongCount":0,"id":"tra-8f3a-5270-abcd-000000000072"},
  {"native_text":"ここで降りなければなりません","target_text":"ต้องลงที่นี่","pronunciation":"tɔ̂ŋ-lōŋ-tʰîː-niī","genre":"基礎共通","memo":"ロン（降りる）。バスやタクシーの目的地で。","favorite":false,"wrongCount":0,"id":"tra-9a4b-6381-bcde-000000000073"},
  {"native_text":"チェックインをお願いします","target_text":"เช็คอินหน่อย","pronunciation":"tɕʰék-ʔīn-nɔ̀y","genre":"基礎共通","memo":"英語由来で通じます。ノイを付けると丁寧。","favorite":false,"wrongCount":0,"id":"tra-0b5c-7492-cdef-000000000074"},
  {"native_text":"予約している〇〇です","target_text":"จองไว้ ชื่อ 〇〇","pronunciation":"tɕɔ̄ːŋ-wáy tɕʰɯ̂ː 〇〇","genre":"基礎共通","memo":"ヂョン（予約する）。タイ語で名前を伝えます。","favorite":false,"wrongCount":0,"id":"tra-1c6d-8503-defa-000000000075"},
  {"native_text":"Wi-Fiのパスワードは何ですか？","target_text":"รหัสไวไฟคืออะไร","pronunciation":"ra-hàt-wāy-fāy-khɯ̄ː-ʔà-rāy","genre":"基礎共通","memo":"ラハッ（コード、パスワード）。","favorite":false,"wrongCount":0,"id":"tra-2d7e-9614-efab-000000000076"},
  {"native_text":"朝食は何時ですか？","target_text":"อาหารเช้ากี่โมง","pronunciation":"ʔaā-hǎːn-tɕʰáːw-kìː-moōŋ","genre":"基礎共通","memo":"アーハーン・チャーオ（朝食）。","favorite":false,"wrongCount":0,"id":"tra-3e8f-0725-fabc-000000000077"},
  {"native_text":"荷物を預かっていただけますか？","target_text":"ฝากกระเป๋าหน่อยได้ไหม","pronunciation":"fàːk-kra-pǎw-nɔ̀y-dâay-mǎy","genre":"基礎共通","memo":"ファーク（預ける）グラパオ（鞄）。チェックアウト後に便利。","favorite":false,"wrongCount":0,"id":"tra-4f9a-1836-abcd-000000000078"},
  {"native_text":"道に迷いました","target_text":"หลงทาง","pronunciation":"lǒŋ-tʰaāŋ","genre":"基礎共通","memo":"ロン（迷う）ターン（道）。迷った時の緊急事態。","favorite":false,"wrongCount":0,"id":"tra-5a0b-2947-bcde-000000000079"},
  {"native_text":"忘れ物をしました","target_text":"ลืมของไว้","pronunciation":"lɯ̄ːm-khɔ̌ːŋ-wáy","genre":"基礎共通","memo":"ルーム（忘れる）コーン（物）。","favorite":false,"wrongCount":0,"id":"tra-6b1c-3058-cdef-000000000080"},
  {"native_text":"気分が悪いです","target_text":"รู้สึกไม่สบาย","pronunciation":"rúː-sùk-mây-sa-baāy","genre":"基礎共通","memo":"ルー・スック（感じる）マイサバイ（不快、不健康）。","favorite":false,"wrongCount":0,"id":"tra-7c2d-4169-defa-000000000081"},
  {"native_text":"警察へ行きたいです","target_text":"อยากไปสถานีตำรวจ","pronunciation":"jàːk-pāy-sa-tʰǎː-niī-tam-rùat","genre":"基礎共通","memo":"ヤークパイ（行きたい）。万が一のトラブルに。","favorite":false,"wrongCount":0,"id":"tra-8d3e-5270-efab-000000000082"},
  {"native_text":"病院へ行きたいです","target_text":"อยากไปโรงพยาบาล","pronunciation":"jàːk-pāy-rōːŋ-pʰa-jaā-baān","genre":"基礎共通","memo":"ローン・パヤーバーン（病院）。","favorite":false,"wrongCount":0,"id":"tra-9e4f-6381-fabc-000000000083"},
  {"native_text":"いらっしゃいませ","target_text":"เชิญครับ/ค่ะ","pronunciation":"tɕʰə̄ːn-kʰráp/khâʔ","genre":"基礎共通","memo":"直訳は「どうぞ」。店や家に入るときに言われます。","favorite":false,"wrongCount":0,"id":"sho-0f5a-7492-abcd-000000000084"},
  {"native_text":"見ているだけです","target_text":"ขอดูเฉยๆ","pronunciation":"khɔ̌ː-duū-tɕʰə̌ːy-tɕʰə̌ːy","genre":"基礎共通","memo":"チュイ・チュイ（ただ単に）。店員の接客を丁寧に断る時。","favorite":false,"wrongCount":0,"id":"sho-1a6b-8503-bcde-000000000085"},
  {"native_text":"これはいくらですか？","target_text":"อันนี้เท่าไหร่","pronunciation":"ʔan-nií-tʰâw-rày","genre":"基礎共通","memo":"タオライ（いくら）。買い物での必須質問。","favorite":false,"wrongCount":0,"id":"sho-2b7c-9614-cdef-000000000086"},
  {"native_text":"1,000円です","target_text":"หนึ่งพันเยน","pronunciation":"nɯ̀ŋ-pʰān-jeēn","genre":"基礎共通","memo":"ヌン・パン（1000）。","favorite":false,"wrongCount":0,"id":"sho-3c8d-0725-defa-000000000087"},
  {"native_text":"これを試着できますか？","target_text":"ขอลองหน่อยได้ไหม","pronunciation":"khɔ̌ː-lɔ̄ːŋ-nɔ̀y-dâay-mǎy","genre":"基礎共通","memo":"ローン（試す）。","favorite":false,"wrongCount":0,"id":"sho-4d9e-1836-efab-000000000088"},
  {"native_text":"他の色はありますか？","target_text":"มีสีอื่นไหม","pronunciation":"miī-sǐː-ʔɯ̀ːn-mǎy","genre":"基礎共通","memo":"シー（色）ウーン（他の）。","favorite":false,"wrongCount":0,"id":"sho-5e0f-2947-fabc-000000000089"},
  {"native_text":"他のサイズはありますか？","target_text":"มีไซส์อื่นไหม","pronunciation":"miī-sáy-ʔɯ̀ːn-mǎy","genre":"基礎共通","memo":"サイズはそのまま通じます（声調に注意）。","favorite":false,"wrongCount":0,"id":"sho-6f1a-3058-abcd-000000000090"},
  {"native_text":"これをください","target_text":"เอาอันนี้","pronunciation":"ʔāw-ʔan-nií","genre":"基礎共通","memo":"アオ（欲しい、取る）。購入決定の意思表示。","favorite":false,"wrongCount":0,"id":"sho-7a2b-4169-bcde-000000000091"},
  {"native_text":"クレジットカードは使えますか？","target_text":"ใช้บัตรเครดิตได้ไหม","pronunciation":"tɕʰáy-bàt-khreō-dìt-dâay-mǎy","genre":"基礎共通","memo":"バット（カード）。","favorite":false,"wrongCount":0,"id":"sho-8b3c-5270-cdef-000000000092"},
  {"native_text":"袋は要りません","target_text":"ไม่เอาถุง","pronunciation":"mây-ʔāw-tʰǔŋ","genre":"基礎共通","memo":"マイ・アオ（要らない）トゥン（袋）。","favorite":false,"wrongCount":0,"id":"sho-9c4d-6381-defa-000000000093"},
  {"native_text":"領収書をください","target_text":"ขอใบเสร็จหน่อย","pronunciation":"khɔ̌ː-bāy-sèt-nɔ̀y","genre":"基礎共通","memo":"バイセッ（領収書、レシート）。","favorite":false,"wrongCount":0,"id":"sho-0d5e-7492-efab-000000000094"},
  {"native_text":"2人ですが、入れますか？","target_text":"สองคน ได้ไหม","pronunciation":"sɔ̌ːŋ-khōn dâay-mǎy","genre":"基礎共通","memo":"ソーン（2）コン（人）。","favorite":false,"wrongCount":0,"id":"res-1e6f-8503-fabc-000000000095"},
  {"native_text":"はい、こちらへどうぞ","target_text":"เชิญด้านนี้ครับ/ค่ะ","pronunciation":"tɕʰə̄ːn-dâːn-nií-kʰráp/khâʔ","genre":"基礎共通","memo":"店員さんに案内される時の言葉。","favorite":false,"wrongCount":0,"id":"res-2f7a-9614-abcd-000000000096"},
  {"native_text":"満席です","target_text":"โต๊ะเต็ม","pronunciation":"tóʔ-tēm","genre":"基礎共通","memo":"ト（テーブル）テム（いっぱい）。","favorite":false,"wrongCount":0,"id":"res-3a8b-0725-bcde-000000000097"},
  {"native_text":"メニューをください","target_text":"ขอเมนูหน่อย","pronunciation":"khɔ̌ː-me-nuū-nɔ̀y","genre":"基礎共通","memo":"メニューを頼む基本表現。","favorite":false,"wrongCount":0,"id":"res-4b9c-1836-cdef-000000000098"},
  {"native_text":"注文をお願いします","target_text":"สั่งอาหารหน่อย","pronunciation":"sàŋ-ʔaā-hǎːn-nɔ̀y","genre":"基礎共通","memo":"サン（注文する）アーハーン（食事）。","favorite":false,"wrongCount":0,"id":"res-5c0d-2947-defa-000000000099"},
  {"native_text":"お勧めは何ですか？","target_text":"แนะนำอะไร","pronunciation":"nɛ́ʔ-nām-ʔà-rāy","genre":"基礎共通","memo":"ネナム（勧める）。店員さんの推奨を聞く時に。","favorite":false,"wrongCount":0,"id":"res-6d1e-3058-efab-000000000100"}
]